{
  "kind": "singleType",
  "collectionName": "home_pages",
  "info": {
    "singularName": "home-page",
    "pluralName": "home-pages",
    "displayName": "homePage"
  },
  "options": {
    "draftAndPublish": true
  },
  "pluginOptions": {},
  "attributes": {
    "heading": {
      "type": "string"
    },
    "subheading": {
      "type": "string"
    },
    "buttonText": {
      "type": "string"
    },
    "aboutHeading": {
      "type": "string"
    },
    "aboutContent": {
      "type": "richtext"
    },
    "aboutButtonText": {
      "type": "string"
    },
    "aboutImage": {
      "allowedTypes": [
        "images",
        "files",
        "videos"
      ],
      "type": "media",
      "multiple": false
    },
    "contactHeading": {
      "type": "string"
    },
    "contactSubHeading": {
      "type": "text"
    }
  }
}
